setup.py
AWS_OOP_distributions.egg-info/PKG-INFO
AWS_OOP_distributions.egg-info/SOURCES.txt
AWS_OOP_distributions.egg-info/dependency_links.txt
AWS_OOP_distributions.egg-info/not-zip-safe
AWS_OOP_distributions.egg-info/top_level.txt
distributions/Binomialdistribution.py
distributions/Gaussiandistribution.py
distributions/Generaldistribution.py
distributions/__init__.py